seura/__init__.py
seura/client.py
seura/config.py
seura/exceptions.py
seura-0.3.0.dist-info/LICENSE
seura-0.3.0.dist-info/METADATA
seura-0.3.0.dist-info/WHEEL
seura-0.3.0.dist-info/top_level.txt
seura-0.3.0.dist-info/RECORD
