Metadata-Version: 2.1
Name: seura
Version: 0.3.0
Summary: Python client for Seura TV IP Control
Author-email: Mickey Schwab <mickeyschwab@gmail.com>
License: MIT License
Requires-Python: >=3.7
License-File: LICENSE
Provides-Extra: dev
Requires-Dist: pytest>=6.0; extra == "dev"
Requires-Dist: pytest-mock>=3.0; extra == "dev"
